koppengeiger/KG_simplified_uint8.tif
koppengeiger/__init__.py
koppengeiger/koppengeiger.py
koppengeiger/version.py
koppengeiger-1.1.0.dist-info/licenses/LICENSE
tests/test_import_dependencies.py
tests/test_import_koppengeiger.py
koppengeiger-1.1.0.dist-info/METADATA
koppengeiger-1.1.0.dist-info/WHEEL
koppengeiger-1.1.0.dist-info/top_level.txt
koppengeiger-1.1.0.dist-info/RECORD
